CHANGELOG
LICENSE
MANIFEST.in
WAIVER
WAIVER.asc
requirements.txt
setup.cfg
setup.py
test_requirements.txt
eth_cache/rpc.py
eth_cache/tx.py
eth_cache.egg-info/PKG-INFO
eth_cache.egg-info/SOURCES.txt
eth_cache.egg-info/dependency_links.txt
eth_cache.egg-info/entry_points.txt
eth_cache.egg-info/requires.txt
eth_cache.egg-info/top_level.txt
eth_cache/store/file.py
eth_cache/store/null.py
tests/test_basic.py